{
  "posts": [
    {
      "id": 1,
      "title": "JS post",
      "body": "Lorem ipsum dolor sit amet, consectetuer adipiscing elit. Donec odio. Quisque volutpat mattis eros."
    },

    {
      "id": 2,
      "title": "Health post",
      "body": "Morbi in sem quis dui placerat ornare. Pellentesque odio nisi, euismod in, pharetra a, ultricies in, diam. Sed arcu. Cras consequat."
    },

    {
      "id": 3,
      "title": "Rest post",
      "body": "Phasellus ultrices nulla quis nibh. Quisque a lectus. Donec consectetuer ligula vulputate sem tristique cursus. "
    }
  ]
}
